smartcard_identifier.py
smartcard_identifier-1.8.9.dist-info/METADATA
smartcard_identifier-1.8.9.dist-info/WHEEL
smartcard_identifier-1.8.9.dist-info/entry_points.txt
smartcard_identifier-1.8.9.dist-info/licenses/LICENSE
smartcard_identifier-1.8.9.dist-info/RECORD
