Metadata-Version: 2.4
Name: smartcard-identifier
Version: 1.8.9
Summary: Read smart card ID number and emulate a keyboard to paste it as text.
Project-URL: Homepage, https://github.com/shortstorybox/smartcard-identifier
Project-URL: Issues, https://github.com/shortstorybox/smartcard-identifier/issues
Author-email: Samuel Hoffstaetter <sam@shortstorybox.com>
License-File: LICENSE
Classifier: License :: OSI Approved :: GNU General Public License v3 or later (GPLv3+)
Classifier: Operating System :: MacOS :: MacOS X
Classifier: Operating System :: Microsoft :: Windows
Classifier: Operating System :: Unix
Classifier: Programming Language :: Python :: 3
Requires-Python: >=3.3
Requires-Dist: pyscard
